pei_docker/__init__.py
pei_docker/_version.py
pei_docker/config_processor.py
pei_docker/merge_build.py
pei_docker/pei.py
pei_docker/pei_utils.py
pei_docker/pei_utils_create.py
pei_docker/examples/environment-variables.yml
pei_docker/examples/gpu-with-host-mount.yml
pei_docker/examples/gpu-with-opengl-win32.yml
pei_docker/examples/minimal-ubuntu-ssh.yml
pei_docker/examples/mount-arbitrary-vol.yml
pei_docker/examples/mount-external-docker-vol.yml
pei_docker/examples/pixi-basic-cpu.yml
pei_docker/examples/pixi-ml-gpu.yml
pei_docker/examples/pixi-with-volumes.yml
pei_docker/examples/python-with-opengl.yml
pei_docker/examples/ssh-keys-inline.yml
pei_docker/examples/with-everything.yml
pei_docker/examples/with-proxy-across-stages.yml
pei_docker/examples/with-proxy-in-build.yml
pei_docker/examples/with-proxy-in-run.yml
pei_docker/examples/with-proxy-manually.yml
pei_docker/project_files/README.md
pei_docker/project_files/stage-1.Dockerfile
pei_docker/project_files/stage-2.Dockerfile
pei_docker/project_files/installation/README.md
pei_docker/project_files/installation/stage-1/README.md
pei_docker/project_files/installation/stage-1/custom/README.md
pei_docker/project_files/installation/stage-1/custom/install-dev-tools.sh
pei_docker/project_files/installation/stage-1/custom/my-build-1.sh
pei_docker/project_files/installation/stage-1/custom/my-build-2.sh
pei_docker/project_files/installation/stage-1/custom/my-on-every-run-1.sh
pei_docker/project_files/installation/stage-1/custom/my-on-every-run-2.sh
pei_docker/project_files/installation/stage-1/custom/my-on-first-run-1.sh
pei_docker/project_files/installation/stage-1/custom/my-on-first-run-2.sh
pei_docker/project_files/installation/stage-1/custom/my-on-user-login-1.sh
pei_docker/project_files/installation/stage-1/custom/my-on-user-login-2.sh
pei_docker/project_files/installation/stage-1/generated/README.md
pei_docker/project_files/installation/stage-1/generated/_custom-on-build.sh
pei_docker-1.2.6.dist-info/METADATA
pei_docker-1.2.6.dist-info/WHEEL
pei_docker-1.2.6.dist-info/entry_points.txt
pei_docker-1.2.6.dist-info/licenses/LICENSE
pei_docker-1.2.6.dist-info/RECORD
