Metadata-Version: 2.4
Name: pei-docker
Version: 1.2.6
Summary: A sophisticated Docker automation framework that transforms YAML configurations into reproducible containerized environments
Project-URL: Homepage, https://github.com/igamenovoer/PeiDocker
Project-URL: Documentation, https://github.com/igamenovoer/PeiDocker
Project-URL: Repository, https://github.com/igamenovoer/PeiDocker
Project-URL: Issues, https://github.com/igamenovoer/PeiDocker/issues
Author-email: igamenovoer <igamenovoer@xx.com>
Maintainer-email: igamenovoer <igamenovoer@xx.com>
License: MIT
License-File: LICENSE
Keywords: automation,containerization,devops,docker,yaml
Classifier: Development Status :: 4 - Beta
Classifier: Environment :: Console
Classifier: Intended Audience :: Developers
Classifier: Intended Audience :: System Administrators
Classifier: License :: OSI Approved :: MIT License
Classifier: Operating System :: OS Independent
Classifier: Programming Language :: Python :: 3
Classifier: Programming Language :: Python :: 3.11
Classifier: Programming Language :: Python :: 3.12
Classifier: Topic :: Software Development :: Build Tools
Classifier: Topic :: System :: Systems Administration
Classifier: Topic :: Utilities
Requires-Python: >=3.11
Requires-Dist: attrs<26,>=25.3.0
Requires-Dist: cattrs<26,>=25.1.1
Requires-Dist: click<9,>=8.2.1
Requires-Dist: nicegui<3,>=2.21.1
Requires-Dist: omegaconf<3,>=2.3.0
Requires-Dist: pywebview<6,>=5.4
Provides-Extra: docs
Requires-Dist: mkdocs-autorefs; extra == 'docs'
Requires-Dist: mkdocs-glightbox; extra == 'docs'
Requires-Dist: mkdocs-material<10,>=9.6.15; extra == 'docs'
Requires-Dist: pymdown-extensions; extra == 'docs'
